{"current_step": 5, "total_steps": 5, "percentage": 100, "message": "\u2705 NGA scraping completed! Found 71 events, created 70 new, updated 0 existing", "timestamp": "2026-01-31T17:41:47.433220", "events_found": 71, "events_saved": 70, "events_updated": 0, "venues_processed": 0, "total_venues": 1, "current_venue": "National Gallery of Art", "recent_events": [{"title": "The Stars We Do Not See", "type": "exhibition", "date": "2025-11-15", "time": null, "location": "East Building"}, {"title": "The Stars We Do Not See", "type": "exhibition", "date": "2025-11-15", "time": null, "location": "East Building"}, {"title": "Back and Forth", "type": "exhibition", "date": "2025-04-26", "time": null, "location": "West Building, Main Floor, Gallery 11"}, {"title": "American Landscapes in Watercolor from the Corcoran Collection", "type": "exhibition", "date": "2025-08-02", "time": null, "location": "West Building, Ground Floor, Gallery 22"}, {"title": "In the Library", "type": "exhibition", "date": "2025-11-24", "time": null, "location": "East Building"}, {"title": "In the Tower: Chakaia Booker", "type": "exhibition", "date": "2025-04-05", "time": null, "location": "East Building"}, {"title": "Clifford Ross", "type": "exhibition", "date": "2026-01-31", "time": null, "location": "West Building"}, {"title": "Mary Cassatt", "type": "exhibition", "date": "2026-01-31", "time": null, "location": "West Building, Main Floor, Gallery 86-88"}, {"title": "Dear America", "type": "exhibition", "date": "2026-01-31", "time": null, "location": "West Building"}, {"title": "Niagara Falls", "type": "exhibition", "date": "2026-01-31", "time": null, "location": "Gallery 72 Ticketing Information"}]}