{"current_step": 3, "total_steps": 3, "percentage": 100, "message": "Scraping complete! Found 3 events.", "timestamp": "2025-12-07T16:51:25.526713", "events_found": 4, "events_saved": 0, "venues_processed": 2, "total_venues": 2, "sources_processed": 0, "total_sources": 0, "current_venue": null, "recent_events": [{"title": "Exhibitions Archive", "venue_id": 167, "event_type": "exhibition", "start_date": "2025-12-07"}, {"title": "Head to Toe: African & Asian Wearables", "venue_id": 167, "event_type": "exhibition", "start_date": "2025-12-07"}, {"title": "Highlights of the Museum", "venue_id": 167, "event_type": "tour", "start_date": "2025-12-07"}]}